hdr_plot/__init__.py
hdr_plot/hdr_plot.py
hdr_plot-0.6.2.data/scripts/hdr-plot
hdr_plot-0.6.2.dist-info/LICENSE
hdr_plot-0.6.2.dist-info/METADATA
hdr_plot-0.6.2.dist-info/WHEEL
hdr_plot-0.6.2.dist-info/top_level.txt
hdr_plot-0.6.2.dist-info/RECORD
