Metadata-Version: 2.1
Name: hdr-plot
Version: 0.6.2
Summary: A simple HdrHistogram plotting script.
Home-page: https://github.com/BrunoBonacci/hdr-plot
Author: Bruno Bonacci
Author-email: bonacci.bruno@gmail.com
License: UNKNOWN
Platform: UNKNOWN
Classifier: Programming Language :: Python :: 3
Classifier: License :: OSI Approved :: Apache Software License
Classifier: Operating System :: OS Independent
License-File: LICENSE
Requires-Dist: matplotlib
Requires-Dist: pandas
